pyintradel/__init__.py
pyintradel/main.py
pyintradel/api/__init__.py
pyintradel/api/parser.py
pyintradel/api/towns.py
pyintradel-0.0.4.dist-info/licenses/LICENSE
pyintradel-0.0.4.dist-info/METADATA
pyintradel-0.0.4.dist-info/WHEEL
pyintradel-0.0.4.dist-info/top_level.txt
pyintradel-0.0.4.dist-info/RECORD
