Metadata-Version: 2.4
Name: pyIntradel
Version: 0.0.4
Summary: Python interface for Intradel
Home-page: https://github.com/thomasgermain/pyintradel.git
Author: Thomas Germain
Author-email: 12560542+thomasgermain@users.noreply.github.com
License: MIT
Classifier: License :: OSI Approved :: MIT License
Classifier: Development Status :: 4 - Beta
Classifier: Programming Language :: Python
Classifier: Programming Language :: Python :: 3.9
Classifier: Programming Language :: Python :: 3.10
Classifier: Topic :: Home Automation
License-File: LICENSE
Requires-Dist: aiohttp<4.0.0,>=3.8.0
Requires-Dist: beautifulsoup4<5.0.0,>=4.11.0
Dynamic: author
Dynamic: author-email
Dynamic: classifier
Dynamic: description
Dynamic: description-content-type
Dynamic: home-page
Dynamic: license
Dynamic: license-file
Dynamic: requires-dist
Dynamic: summary
